rfb_mc/__init__.py
rfb_mc/helper.py
rfb_mc/integrator.py
rfb_mc/py.typed
rfb_mc/restrictive_formula_module.py
rfb_mc/restrictive_formula_module_implementation.py
rfb_mc/runner.py
rfb_mc/scheduler.py
rfb_mc/serialization.py
rfb_mc/store.py
rfb_mc/types.py
rfb_mc/component/__init__.py
rfb_mc/component/direct_integrator.py
rfb_mc/component/direct_integrator_z3.py
rfb_mc/component/in_memory_store.py
rfb_mc/component/multi_processing_integrator.py
rfb_mc/component/multi_processing_integrator_z3.py
rfb_mc/component/runner_z3.py
rfb_mc/component/aws/__init__.py
rfb_mc/component/aws/dynamodb_store.py
rfb_mc/component/eamp/__init__.py
rfb_mc/component/eamp/eamp_edge_scheduler.py
rfb_mc/component/eamp/eamp_edge_scheduler_base.py
rfb_mc/component/eamp/eamp_edge_scheduler_sp.py
rfb_mc/component/eamp/eamp_rfm.py
rfb_mc/component/eamp/eamp_rfmi_z3.py
rfb_mc/component/eamp/primes.py
rfb_mc/component/eamp/types.py
rfb_mc/component/eamp/utility.py
rfb_mc/component/helper/__init__.py
rfb_mc/component/helper/z3_helper.py
rfb_mc-0.0.23.dist-info/LICENSE
rfb_mc-0.0.23.dist-info/METADATA
rfb_mc-0.0.23.dist-info/WHEEL
rfb_mc-0.0.23.dist-info/top_level.txt
rfb_mc-0.0.23.dist-info/RECORD
